<?xml-stylesheet href="xsltforms/xsltforms.xsl" type="text/xsl"?>
<?xsltforms-options debug="yes"?>
<problem>
	<creation-date>2015-12-01</creation-date>
	<id>problem2</id>
	<category>Pirotecnia</category>
	<title>No me dejaron dormir con la tal alborada</title>
	<description>Las personas han convertido el verdadero significado de alborada en alboroto y escandalo</description>
	<user>Marleny</user>
</problem>
<solution>
	<creation-date>2015-12-01</creation-date>		
	<title>Duerme con los oidos tapados</title>
	<description>Deberias dormir con los oidos tapados y asi contemplar mejor el sueño</description>
	<user>Mariana</user>
<solution>
<solution>
	<creation-date>2015-12-01</creation-date>		
	<title>Que inpongan una ley para los que quemen polvora</title>
	<description>Deberian aplicar una multa bien grande a las personas que quemen polvora inconscientemente</description>
	<user>ramiro-1990</user>
<solution>
<solution>
	<creation-date>2015-12-02</creation-date>		
	<title>Cuando no puedes con el enemigo, unetele!</title>
	<description>Me pasaba igual, pero en cuanto vi que la polvora no iba a acabar, me levante, me vesti y me uní a los que estaban tirando polvora</description>
	<user>estebacano</user>
<solution>